{"cameraMode":{"drawMode":0,"name":"Shaded","section":"Shading Mode"},"sceneLighting":false,"audioPlay":false,"sceneViewState":{"m_AlwaysRefresh":false,"showFog":true,"showSkybox":false,"showFlares":true,"showImageEffects":true,"showParticleSystems":true,"showVisualEffectGraphs":true,"m_FxEnabled":true},"in2DMode":false,"pivot":{"x":-6.862916946411133,"y":2.3820436000823976,"z":27.525226593017579},"rotation":{"x":-0.2918005585670471,"y":0.30959057807922366,"z":-0.1036260575056076,"w":-0.8983863592147827},"size":8.053932189941407,"orthographic":false}